bitfinex/__init__.py
bitfinex/bitfinex_v1.py
bitfinex/bitfinex_v2.py
bitfinex_tencars-0.0.3.dist-info/DESCRIPTION.rst
bitfinex_tencars-0.0.3.dist-info/METADATA
bitfinex_tencars-0.0.3.dist-info/RECORD
bitfinex_tencars-0.0.3.dist-info/WHEEL
bitfinex_tencars-0.0.3.dist-info/metadata.json
bitfinex_tencars-0.0.3.dist-info/top_level.txt
