Metadata-Version: 2.0
Name: bitfinex-tencars
Version: 0.0.3
Summary: Bitfinex REST API client
Home-page: https://github.com/akcarsten/bitfinex_api
Author: Carsten Klein
Author-email: UNKNOWN
License: UNKNOWN
Platform: UNKNOWN
Classifier: Programming Language :: Python :: 3
Classifier: License :: OSI Approved :: MIT License
Classifier: Operating System :: OS Independent
